jupyter_spy/__init__.py
jupyter_spy/__main__.py
jupyter_spy/proc.py
jupyter_spy/session_hook.py
jupyter_spy/spy.py
jupyter_spy-1.0.0.dist-info/DESCRIPTION.rst
jupyter_spy-1.0.0.dist-info/METADATA
jupyter_spy-1.0.0.dist-info/RECORD
jupyter_spy-1.0.0.dist-info/WHEEL
jupyter_spy-1.0.0.dist-info/metadata.json
jupyter_spy-1.0.0.dist-info/pbr.json
jupyter_spy-1.0.0.dist-info/top_level.txt
