Metadata-Version: 2.0
Name: jupyter-spy
Version: 1.0.0
Summary: Log Jupyter messages
Home-page: https://github.com/vidartf/jupyter-spy
Author: Vidar T. Fauske
Author-email: vidartf@gmail.com
License: BSD-3-Clause
Keywords: jupyter
